sdna/CONTEXT_ENGINEERING_DESIGN.md
sdna/CONTEXT_ENGINEERING_PLAN.md
sdna/__init__.py
sdna/ariadne.py
sdna/brain.py
sdna/code_agent.py
sdna/config.py
sdna/context_engineering.py
sdna/defaults.py
sdna/duo.py
sdna/duo_v2.py
sdna/poimandres.py
sdna/runner.py
sdna/sdna.py
sdna/state.py
sdna/tags.py
sdna/tools.py
sanctuary_dna-0.3.4.dist-info/METADATA
sanctuary_dna-0.3.4.dist-info/WHEEL
sanctuary_dna-0.3.4.dist-info/RECORD
