Metadata-Version: 2.4
Name: sanctuary-dna
Version: 0.3.4
Summary: Sanctuary DNA - Gnostic agent workflow DSL. Ariadne (threading) + Poimandres (generation) = SDNA spiral
Project-URL: Homepage, https://github.com/sancovp/sdna
Project-URL: Repository, https://github.com/sancovp/sdna
Author-email: Isaac Wostrel-Rubin <isaac@sancovp.com>
License: MIT
Keywords: agent,anthropic,claude,composition,sdk,workflow
Classifier: Development Status :: 3 - Alpha
Classifier: Intended Audience :: Developers
Classifier: License :: OSI Approved :: MIT License
Classifier: Programming Language :: Python :: 3
Classifier: Programming Language :: Python :: 3.10
Classifier: Programming Language :: Python :: 3.11
Classifier: Programming Language :: Python :: 3.12
Requires-Python: >=3.10
Requires-Dist: anthropic>=0.40.0
Requires-Dist: langgraph>=0.2.0
Requires-Dist: pydantic>=2.0
Provides-Extra: dev
Requires-Dist: pytest-asyncio>=0.21; extra == 'dev'
Requires-Dist: pytest>=7.0; extra == 'dev'
